{
  "Grid": {
    "autoColumns": {
      "type": "SystemStyleObject[\"gridAutoColumns\"]",
      "required": false,
      "description": "Shorthand prop for `gridAutoColumns`"
    },
    "autoFlow": {
      "type": "SystemStyleObject[\"gridAutoFlow\"]",
      "required": false,
      "description": "Shorthand prop for `gridAutoFlow`"
    },
    "autoRows": {
      "type": "SystemStyleObject[\"gridAutoRows\"]",
      "required": false,
      "description": "Shorthand prop for `gridAutoRows`"
    },
    "column": {
      "type": "SystemStyleObject[\"gridColumn\"]",
      "required": false,
      "description": "Shorthand prop for `gridColumn`"
    },
    "columnGap": {
      "type": "SystemStyleObject[\"gridColumnGap\"]",
      "required": false,
      "description": "Shorthand prop for `gridColumnGap`"
    },
    "gap": {
      "type": "SystemStyleObject[\"gridGap\"]",
      "required": false,
      "description": "Shorthand prop for `gridGap`"
    },
    "row": {
      "type": "SystemStyleObject[\"gridRow\"]",
      "required": false,
      "description": "Shorthand prop for `gridRow`"
    },
    "rowGap": {
      "type": "SystemStyleObject[\"gridRowGap\"]",
      "required": false,
      "description": "Shorthand prop for `gridRowGap`"
    },
    "templateAreas": {
      "type": "SystemStyleObject[\"gridTemplateAreas\"]",
      "required": false,
      "description": "Shorthand prop for `gridTemplateAreas`"
    },
    "templateColumns": {
      "type": "SystemStyleObject[\"gridTemplateColumns\"]",
      "required": false,
      "description": "Shorthand prop for `gridTemplateColumns`"
    },
    "templateRows": {
      "type": "SystemStyleObject[\"gridTemplateRows\"]",
      "required": false,
      "description": "Shorthand prop for `gridTemplateRows`"
    }
  },
  "GridItem": {
    "area": {
      "type": "SystemStyleObject[\"gridArea\"]",
      "required": false,
      "description": "Shorthand prop for `gridArea`"
    },
    "colEnd": {
      "type": "ConditionalValue<number | \"auto\">",
      "required": false
    },
    "colSpan": {
      "type": "ConditionalValue<number | \"auto\">",
      "required": false,
      "description": "The number of columns the grid item should `span`."
    },
    "colStart": {
      "type": "ConditionalValue<number | \"auto\">",
      "required": false,
      "description": "The column number the grid item should start."
    },
    "rowEnd": {
      "type": "ConditionalValue<number | \"auto\">",
      "required": false
    },
    "rowSpan": {
      "type": "ConditionalValue<number | \"auto\">",
      "required": false
    },
    "rowStart": {
      "type": "ConditionalValue<number | \"auto\">",
      "required": false
    }
  },
  "SimpleGrid": {
    "autoColumns": {
      "required": false,
      "description": "Shorthand prop for `gridAutoColumns`"
    },
    "autoFlow": {
      "required": false,
      "description": "Shorthand prop for `gridAutoFlow`"
    },
    "autoRows": {
      "required": false,
      "description": "Shorthand prop for `gridAutoRows`"
    },
    "column": {
      "required": false,
      "description": "Shorthand prop for `gridColumn`"
    },
    "columnGap": {
      "required": false,
      "description": "Shorthand prop for `gridColumnGap`"
    },
    "columns": {
      "type": "ConditionalValue<number>",
      "required": false,
      "description": "The number of columns"
    },
    "gap": { "required": false, "description": "Shorthand prop for `gridGap`" },
    "minChildWidth": {
      "type": "GridProps[\"minWidth\"]",
      "required": false,
      "description": "The width at which child elements will break into columns. Pass a number for pixel values or a string for any other valid CSS length."
    },
    "row": { "required": false, "description": "Shorthand prop for `gridRow`" },
    "rowGap": {
      "required": false,
      "description": "Shorthand prop for `gridRowGap`"
    },
    "templateAreas": {
      "required": false,
      "description": "Shorthand prop for `gridTemplateAreas`"
    },
    "templateColumns": {
      "required": false,
      "description": "Shorthand prop for `gridTemplateColumns`"
    },
    "templateRows": {
      "required": false,
      "description": "Shorthand prop for `gridTemplateRows`"
    }
  }
}
